{
  "get":[
	 { "Task Name": "Todo list component", "Date" : "06 Jun 2021", "Completion" : true, "Reminder": false },
	 { "Task Name": "Udemy course", "Date" : "22 Jun 2021", "Completion" : false, "Reminder": true },
	 { "Task Name": "Training", "Date" : "22 Jun 2021", "Completion" : false, "Reminder": false }
  ],
  "add": [
 	{ "Task Name": "Todo list component", "Date" : "06 Jun 2021", "Completion" : true, "Reminder": false },
	{ "Task Name": "Udemy course", "Date" : "22 Jun 2021", "Completion" : false, "Reminder": false },
	{ "Task Name": "Training", "Date" : "22 Jun 2021", "Completion" : false, "Reminder": true },
	{ "Task Name": "Todo list component 2", "Date" : "07 Jun 2021", "Completion" : false, "Reminder": false }
  ],
  "completeAll": [
 	{ "Task Name": "Todo list component", "Date" : "22 Jul 2021", "Completion" : true, "Reminder": false },
	{ "Task Name": "Udemy course", "Date" : "22 Jul 2021", "Completion" : true, "Reminder": true },
	{ "Task Name": "Training", "Date" : "22 Jul 2021", "Completion" : true, "Reminder": false }
  ],
  "deleteAll": []
}
